{
  "project_info": {
    "project_number": "1059503121530",
    "firebase_url": "https://le-space-webrtc.firebaseio.com",
    "project_id": "le-space-webrtc",
    "storage_bucket": "le-space-webrtc.appspot.com"
  },
  "client": [
    {
      "client_info": {
        "mobilesdk_app_id": "1:1059503121530:android:f36173e948059ccb",
        "android_client_info": {
          "package_name": "de.lespace.apprtc"
        }
      },
      "oauth_client": [
        {
          "client_id": "1059503121530-ed58ln2s813feeu2v7speinm759f99qu.apps.googleusercontent.com",
          "client_type": 3
        }
      ],
      "api_key": [
        {
          "current_key": "AIzaSyB1lKLIZ_9wixONhxQlcDUo6lrNU1AUNSM"
        }
      ],
      "services": {
        "analytics_service": {
          "status": 1
        },
        "appinvite_service": {
          "status": 1,
          "other_platform_oauth_client": []
        },
        "ads_service": {
          "status": 2
        }
      }
    }
  ],
  "configuration_version": "1"
}
